django_cmd.py
hatch_autorun_django_cmd.pth
django_cmd-3.0.dist-info/METADATA
django_cmd-3.0.dist-info/WHEEL
django_cmd-3.0.dist-info/entry_points.txt
django_cmd-3.0.dist-info/licenses/LICENSE
django_cmd-3.0.dist-info/RECORD
